.coveragerc
CONTRIBUTING.md
LICENCE
MANIFEST.in
Makefile
README.rst
logo.png
setup.cfg
setup.py
tox.ini
tqdm.1
examples/7zx.py
examples/include_no_requirements.py
examples/pandas_progress_apply.py
examples/parallel_bars.py
examples/redirect_print.py
examples/simple_examples.py
examples/tqdm_wget.py
tqdm/__init__.py
tqdm/__main__.py
tqdm/_main.py
tqdm/_monitor.py
tqdm/_tqdm.py
tqdm/_tqdm_gui.py
tqdm/_tqdm_notebook.py
tqdm/_tqdm_pandas.py
tqdm/_utils.py
tqdm/_version.py
tqdm/auto/__init__.py
tqdm/autonotebook/__init__.py
tqdm/tests/tests_main.py
tqdm/tests/tests_pandas.py
tqdm/tests/tests_perf.py
tqdm/tests/tests_synchronisation.py
tqdm/tests/tests_tqdm.py
tqdm/tests/tests_version.py
tqdm_conan.egg-info/PKG-INFO
tqdm_conan.egg-info/SOURCES.txt
tqdm_conan.egg-info/dependency_links.txt
tqdm_conan.egg-info/entry_points.txt
tqdm_conan.egg-info/top_level.txt